MANIFEST.in
setup.py
./__init__.py
./__openerp__.py
i18n/ar.po
i18n/bs.po
i18n/cs.po
i18n/da.po
i18n/de.po
i18n/en_AU.po
i18n/en_GB.po
i18n/es.po
i18n/es_DO.po
i18n/es_EC.po
i18n/es_MX.po
i18n/et.po
i18n/fa.po
i18n/fi.po
i18n/fr.po
i18n/he.po
i18n/hr.po
i18n/hu.po
i18n/it.po
i18n/ko.po
i18n/lt.po
i18n/lv.po
i18n/mk.po
i18n/mn.po
i18n/nb.po
i18n/nl.po
i18n/nl_BE.po
i18n/pl.po
i18n/pt.po
i18n/pt_BR.po
i18n/ro.po
i18n/ru.po
i18n/sl.po
i18n/sv.po
i18n/th.po
i18n/tr.po
i18n/web_view_editor.pot
i18n/zh_CN.po
openerp_web_view_editor.egg-info/PKG-INFO
openerp_web_view_editor.egg-info/SOURCES.txt
openerp_web_view_editor.egg-info/dependency_links.txt
openerp_web_view_editor.egg-info/requires.txt
openerp_web_view_editor.egg-info/top_level.txt
static/src/js/view_editor.js
static/src/xml/view_editor.xml